booknlp_fr/__init__.py
booknlp_fr/booknlp_fr_add_entities_features.py
booknlp_fr/booknlp_fr_coreference_resolution_module.py
booknlp_fr/booknlp_fr_extract_attributes.py
booknlp_fr/booknlp_fr_gender.py
booknlp_fr/booknlp_fr_generate_characters_dict.py
booknlp_fr/booknlp_fr_generate_sacr_file.py
booknlp_fr/booknlp_fr_generate_tokens_and_entities_from_sacr.py
booknlp_fr/booknlp_fr_generate_tokens_df.py
booknlp_fr/booknlp_fr_generate_tokens_embeddings_tensor.py
booknlp_fr/booknlp_fr_load_save_functions.py
booknlp_fr/booknlp_fr_mentions_detection_module.py
booknlp_fr/booknlp_fr_number.py
booknlp_fr/data/insee_names_fr_1900_2023.csv
booknlp_fr-0.0.73.dist-info/METADATA
booknlp_fr-0.0.73.dist-info/WHEEL
booknlp_fr-0.0.73.dist-info/top_level.txt
booknlp_fr-0.0.73.dist-info/RECORD
